cerberus_monitor/__init__.py
cerberus_monitor/main.py
cerberus_monitor/prompts.py
cerberus_monitor-2025.12.20190018.dist-info/METADATA
cerberus_monitor-2025.12.20190018.dist-info/WHEEL
cerberus_monitor-2025.12.20190018.dist-info/top_level.txt
cerberus_monitor-2025.12.20190018.dist-info/RECORD
