Metadata-Version: 2.4
Name: cerberus-monitor
Version: 2025.12.20190018
Summary: Cerberus: A Simplified Network Monitoring Solution that Empowers Users to Extract Insightful Insights from Network Activity in Real-Time.
Author-email: cerberus-monitor <hi@eugene.plus>
License: MIT
Project-URL: Homepage, https://github.com/chigwell/cerberus-monitor
Requires-Python: >=3.9
Requires-Dist: langchain-llm7>=0.0.0
Requires-Dist: llmatch-messages>=0.0.0
Requires-Dist: langchain-core>=0.3.0
